{
  "resources": [
    {
      "path": "data.csv",
      "name": "data",
      "profile": "tabular-data-resource",
      "scheme": "file",
      "format": "csv",
      "hashing": "md5",
      "encoding": "utf-8",
      "schema": {
        "fields": [
          {
            "name": "Value",
            "type": "number",
            "title": "Value"
          },
          {
            "name": "Year",
            "type": "number",
            "title": "Year"
          }
        ]
      }
    }
  ],
  "profile": "data-package",
  "name": "11-7-1",
  "title": "도시에서 공공목적의 용도를 위해 개방된 공용 공간이 차지하는 평균비율 (연령, 성 및 장애별)"
}